<?xml version="1.0" ?>

<!--****************************************************-->
<!--****   Fall of the Republic: Foerost Campaign   ****-->
<!--****************************************************-->

<Story_Mode_Plots>
	<Lua_Script>GCFoerost</Lua_Script>
	<Active_Plot>Conquests\CloneWarsFoerost\Story_Sandbox_Foerost_CIS.XML</Active_Plot>
	<Active_Plot>Conquests\Story_Sandbox_Universal_Lock_CIS.xml</Active_Plot>

	<Lua_Script>GovernmentHandlerCIS</Lua_Script>
	<Active_Plot>Conquests\Story_Sandbox_Government_CIS.xml</Active_Plot>

	<Active_Plot>Conquests\Factional_Buildable_REBEL.xml</Active_Plot>

	<Active_Plot>Conquests\Events\MissionRepository_REBEL.xml</Active_Plot>
</Story_Mode_Plots>